{
  "kind": "collectionType",
  "collectionName": "stories",
  "info": {
    "name": "Story"
  },
  "options": {
    "increments": true,
    "timestamps": true,
    "draftAndPublish": true
  },
  "attributes": {
    "title": {
      "type": "string"
    },
    "images": {
      "collection": "file",
      "via": "related",
      "allowedTypes": [
        "images",
        "files",
        "videos"
      ],
      "plugin": "upload",
      "required": false
    },
    "thumb": {
      "type": "integer"
    },
    "idea": {
      "type": "richtext"
    }
  }
}
